dormouse/__init__.py
dormouse/_bool_parser.py
dormouse/_bool_parser_test.py
dormouse-0.1.dist-info/DESCRIPTION.rst
dormouse-0.1.dist-info/METADATA
dormouse-0.1.dist-info/RECORD
dormouse-0.1.dist-info/WHEEL
dormouse-0.1.dist-info/metadata.json
dormouse-0.1.dist-info/top_level.txt
