Metadata-Version: 2.0
Name: dormouse
Version: 0.1
Summary: Parsing Python code into Boolean expressions
Home-page: http://github.com/msoeken/dormouse
Author: Mathias Soeken
Author-email: mathias.soeken@epfl.ch
License: MIT
Platform: UNKNOWN
Requires-Dist: sympy
